base91/__init__.py
base91-1.0.1.dist-info/DESCRIPTION.rst
base91-1.0.1.dist-info/METADATA
base91-1.0.1.dist-info/RECORD
base91-1.0.1.dist-info/WHEEL
base91-1.0.1.dist-info/metadata.json
base91-1.0.1.dist-info/top_level.txt
