Metadata-Version: 1.0
Name: base91
Version: 1.0.1
Summary: Base91 encoding in Python
Home-page: https://github.com/SunDwarf/base91-python
Author: UNKNOWN
Author-email: UNKNOWN
License: New BSD
Platform: UNKNOWN
